Metadata-Version: 2.4
Name: Warg
Version: 1.4.9
Summary: A package for easing return of multiple values
Home-page: https://github.com/pything/warg
Download-URL: https://github.com/pything/warg/releases
Author: Christian Heider Lindbjerg
Author-email: christian.heider@alexandra.dk
Maintainer: Christian Heider Lindbjerg
Maintainer-email: christian.heider@alexandra.dk
License: Apache License, Version 2.0
Keywords: python interface api
Classifier: Development Status :: 4 - Beta
Classifier: Environment :: Console
Classifier: Intended Audience :: End Users/Desktop
Classifier: Intended Audience :: Developers
Classifier: License :: OSI Approved :: Apache Software License
Classifier: Operating System :: MacOS :: MacOS X
Classifier: Operating System :: Microsoft :: Windows
Classifier: Operating System :: POSIX
Classifier: Operating System :: OS Independent
Classifier: Programming Language :: Python :: 3
Classifier: Natural Language :: English
Requires-Python: >=3.6
License-File: LICENSE.md
Provides-Extra: docs
Requires-Dist: sphinxcontrib-programoutput; extra == "docs"
Requires-Dist: warg; extra == "docs"
Requires-Dist: apppath; extra == "docs"
Requires-Dist: sphinx; extra == "docs"
Provides-Extra: setup
Requires-Dist: pytest-runner; extra == "setup"
Provides-Extra: dev
Requires-Dist: sphinxcontrib-programoutput; extra == "dev"
Requires-Dist: twine>=1.13.0; extra == "dev"
Requires-Dist: pytest-runner; extra == "dev"
Requires-Dist: wheel>=0.38.0; extra == "dev"
Requires-Dist: warg; extra == "dev"
Requires-Dist: black>=18.9b0; extra == "dev"
Requires-Dist: pip>=19.0.3; extra == "dev"
Requires-Dist: apppath; extra == "dev"
Requires-Dist: pytest-cov>=2.6.1; extra == "dev"
Requires-Dist: pytest>=4.3.0; extra == "dev"
Requires-Dist: tox; extra == "dev"
Requires-Dist: sphinx; extra == "dev"
Requires-Dist: coveralls>=1.6.0; extra == "dev"
Provides-Extra: tests
Requires-Dist: tox; extra == "tests"
Requires-Dist: pytest-cov>=2.6.1; extra == "tests"
Requires-Dist: pytest>=4.3.0; extra == "tests"
Provides-Extra: all
Requires-Dist: sphinxcontrib-programoutput; extra == "all"
Requires-Dist: twine>=1.13.0; extra == "all"
Requires-Dist: pytest-runner; extra == "all"
Requires-Dist: wheel>=0.38.0; extra == "all"
Requires-Dist: warg; extra == "all"
Requires-Dist: black>=18.9b0; extra == "all"
Requires-Dist: pip>=19.0.3; extra == "all"
Requires-Dist: apppath; extra == "all"
Requires-Dist: pytest-cov>=2.6.1; extra == "all"
Requires-Dist: pytest>=4.3.0; extra == "all"
Requires-Dist: tox; extra == "all"
Requires-Dist: sphinx; extra == "all"
Requires-Dist: coveralls>=1.6.0; extra == "all"
Dynamic: author
Dynamic: author-email
Dynamic: classifier
Dynamic: description
Dynamic: description-content-type
Dynamic: download-url
Dynamic: home-page
Dynamic: keywords
Dynamic: license
Dynamic: license-file
Dynamic: maintainer
Dynamic: maintainer-email
Dynamic: provides-extra
Dynamic: requires-python
Dynamic: summary
